pfund/CONTRIBUTING.md
pfund/__init__.py
pfund/accounts/__init__.py
pfund/accounts/account_base.py
pfund/accounts/account_crypto.py
pfund/accounts/account_ib.py
pfund/adapter.py
pfund/analyzer.py
pfund/backtest_history.py
pfund/balances/__init__.py
pfund/balances/balance_base.py
pfund/balances/balance_crypto.py
pfund/balances/balance_ib.py
pfund/brokers/__init__.py
pfund/brokers/broker_backtest.py
pfund/brokers/broker_base.py
pfund/brokers/broker_crypto.py
pfund/brokers/broker_defi.py
pfund/brokers/broker_live.py
pfund/brokers/ib/__init__.py
pfund/brokers/ib/broker_ib.py
pfund/brokers/ib/ib_api.py
pfund/brokers/ib/ib_client.py
pfund/brokers/ib/ib_wrapper.py
pfund/cli/__init__.py
pfund/cli/commands/__init__.py
pfund/cli/commands/config.py
pfund/cli/commands/docker_compose.py
pfund/cli/main.py
pfund/config/binance/linear/config.yml
pfund/config/binance/linear/lot_sizes_linear.yml
pfund/config/binance/linear/pdt_matchings_linear.yml
pfund/config/binance/linear/tick_sizes_linear.yml
pfund/config/bybit/config.yml
pfund/config/bybit/lot_sizes_inverse.yml
pfund/config/bybit/lot_sizes_linear.yml
pfund/config/bybit/lot_sizes_option.yml
pfund/config/bybit/lot_sizes_spot.yml
pfund/config/bybit/pdt_matchings_inverse.yml
pfund/config/bybit/pdt_matchings_linear.yml
pfund/config/bybit/pdt_matchings_option.yml
pfund/config/bybit/pdt_matchings_spot.yml
pfund/config/bybit/tick_sizes_inverse.yml
pfund/config/bybit/tick_sizes_linear.yml
pfund/config/bybit/tick_sizes_option.yml
pfund/config/bybit/tick_sizes_spot.yml
pfund/config/configuration.py
pfund/config/ib/config.yml
pfund/config_handler.py
pfund/const/__init__.py
pfund/const/_zmq_routes.py
pfund/const/aliases.py
pfund/const/common.py
pfund/const/paths.py
pfund/data_tools/data_tool_base.py
pfund/data_tools/data_tool_pandas.py
pfund/data_tools/data_tool_polars.py
pfund/datas/__init__.py
pfund/datas/data_bar.py
pfund/datas/data_base.py
pfund/datas/data_quote.py
pfund/datas/data_tick.py
pfund/datas/data_time_based.py
pfund-0.0.2.dist-info/LICENSE
pfund-0.0.2.dist-info/METADATA
pfund-0.0.2.dist-info/WHEEL
pfund-0.0.2.dist-info/entry_points.txt
pfund-0.0.2.dist-info/RECORD
