Metadata-Version: 2.1
Name: pfund
Version: 0.0.2
Summary: A Complete Algo-Trading Framework for Machine Learning, enabling trading across TradFi, CeFi and DeFi. Supports Vectorized and Event-Driven Backtesting, Paper and Live Trading
Home-page: https://pfund.ai
License: Apache-2.0
Keywords: trading,algo-trading,stocks,cryptos,cryptocurrencies,TradFi,CeFi,DeFi,portfolio management,investment,backtesting,machine learning
Author: Stephen Yau
Author-email: softwareentrepreneer+pfund@gmail.com
Requires-Python: >=3.10,<4.0
Classifier: Intended Audience :: Developers
Classifier: Intended Audience :: Financial and Insurance Industry
Classifier: Intended Audience :: Information Technology
Classifier: Intended Audience :: Science/Research
Classifier: License :: OSI Approved :: Apache Software License
Classifier: Operating System :: OS Independent
Classifier: Programming Language :: Python :: 3
Classifier: Programming Language :: Python :: 3.10
Classifier: Programming Language :: Python :: 3.11
Classifier: Programming Language :: Python :: 3.12
Classifier: Programming Language :: Python :: 3.13
Classifier: Topic :: Office/Business :: Financial :: Investment
Classifier: Topic :: Scientific/Engineering :: Artificial Intelligence
Classifier: Topic :: Software Development :: Libraries :: Application Frameworks
Provides-Extra: all
Provides-Extra: data
Provides-Extra: fe
Provides-Extra: ml
Provides-Extra: stats
Provides-Extra: train
Requires-Dist: click (>=8.1.7,<9.0.0)
Requires-Dist: duckdb (>=1.0.0,<2.0.0)
Requires-Dist: feast (>=0.40.1,<0.41.0) ; extra == "fe" or extra == "all"
Requires-Dist: gitpython (>=3.1.43,<4.0.0)
Requires-Dist: ipython (>=8.23.0,<9.0.0)
Requires-Dist: mlflow (>=2.16.1,<3.0.0) ; extra == "ml" or extra == "all"
Requires-Dist: optuna (>=4.0.0,<5.0.0) ; extra == "train" or extra == "all"
Requires-Dist: orjson (>=3.10.1,<4.0.0)
Requires-Dist: papermill (>=2.6.0,<3.0.0) ; extra == "stats" or extra == "all"
Requires-Dist: pfeed[all] (>=0.0.2,<0.0.3) ; extra == "data" or extra == "all"
Requires-Dist: pfolio (>=0.0.1.dev4,<0.0.2) ; extra == "stats" or extra == "train" or extra == "all"
Requires-Dist: platformdirs (>=4.3.6,<5.0.0)
Requires-Dist: python-dotenv (>=1.0.1,<2.0.0)
Requires-Dist: python-telegram-bot (>=21.5,<22.0)
Requires-Dist: pyyaml (>=6.0.1,<7.0.0)
Requires-Dist: pyzmq (>=26.2.0,<27.0.0) ; extra == "data" or extra == "all"
Requires-Dist: redis[hiredis] (>=5.1.1,<6.0.0) ; extra == "data" or extra == "all"
Requires-Dist: requests (>=2.31.0,<3.0.0)
Requires-Dist: rich (>=13.7.1,<14.0.0)
Requires-Dist: schedule (>=1.2.2,<2.0.0)
Requires-Dist: scikit-learn (>=1.5.2,<2.0.0) ; extra == "ml" or extra == "all"
Requires-Dist: streamlit (>=1.39.0,<2.0.0) ; extra == "train" or extra == "all"
Requires-Dist: ta (>=0.11.0,<0.12.0) ; extra == "fe" or extra == "all"
Requires-Dist: torch (>=2.4.1,<3.0.0) ; extra == "ml" or extra == "all"
Requires-Dist: tqdm (>=4.66.2,<5.0.0)
Requires-Dist: trogon (>=0.6.0,<0.7.0)
Requires-Dist: tsfresh (>=0.20.3,<0.21.0) ; extra == "fe" or extra == "all"
Requires-Dist: voila (>=0.5.7,<0.6.0) ; extra == "stats" or extra == "all"
Requires-Dist: websocket-client (>=1.8.0,<2.0.0)
Project-URL: Documentation, https://pfund-docs.pfund.ai
Project-URL: Repository, https://github.com/PFund-Software-Ltd/pfund
